{"nodes":[{"id":"scorecanvas_scorecanvas","label":"ScoreCanvas Component","file_type":"code","source_file":"MuseCore/src/ui/components/ScoreCanvas.tsx","source_location":null,"source_url":null,"captured_at":null,"author":null,"contributor":null},{"id":"scorecanvas_sectionoverlay","label":"SectionOverlay (internal)","file_type":"code","source_file":"MuseCore/src/ui/components/ScoreCanvas.tsx","source_location":null,"source_url":null,"captured_at":null,"author":null,"contributor":null},{"id":"scorecanvas_playabilityoverlay","label":"PlayabilityOverlay (internal)","file_type":"code","source_file":"MuseCore/src/ui/components/ScoreCanvas.tsx","source_location":null,"source_url":null,"captured_at":null,"author":null,"contributor":null},{"id":"scorecanvas_limboverlay","label":"LimbOverlay (internal)","file_type":"code","source_file":"MuseCore/src/ui/components/ScoreCanvas.tsx","source_location":null,"source_url":null,"captured_at":null,"author":null,"contributor":null},{"id":"scorecanvas_playhead_cursor","label":"Playhead Cursor (RAF animation)","file_type":"code","source_file":"MuseCore/src/ui/components/ScoreCanvas.tsx","source_location":null,"source_url":null,"captured_at":null,"author":null,"contributor":null},{"id":"scorecanvas_click_preview","label":"Click-to-Preview Note Feature","file_type":"code","source_file":"MuseCore/src/ui/components/ScoreCanvas.tsx","source_location":null,"source_url":null,"captured_at":null,"author":null,"contributor":null},{"id":"sectiontimeline_sectiontimeline","label":"SectionTimeline Component","file_type":"code","source_file":"MuseCore/src/ui/components/SectionTimeline.tsx","source_location":null,"source_url":null,"captured_at":null,"author":null,"contributor":null},{"id":"sectiontimeline_playabilitybadge","label":"PlayabilityBadge (internal)","file_type":"code","source_file":"MuseCore/src/ui/components/SectionTimeline.tsx","source_location":null,"source_url":null,"captured_at":null,"author":null,"contributor":null},{"id":"settingsmodal_settingsmodal","label":"SettingsModal Component","file_type":"code","source_file":"MuseCore/src/ui/components/SettingsModal.tsx","source_location":null,"source_url":null,"captured_at":null,"author":null,"contributor":null},{"id":"topbar_topbar","label":"TopBar Component","file_type":"code","source_file":"MuseCore/src/ui/components/TopBar.tsx","source_location":null,"source_url":null,"captured_at":null,"author":null,"contributor":null},{"id":"transportbar_transportbar","label":"TransportBar Component","file_type":"code","source_file":"MuseCore/src/ui/components/TransportBar.tsx","source_location":null,"source_url":null,"captured_at":null,"author":null,"contributor":null},{"id":"transportbar_mixerstrip","label":"MixerStrip (inline)","file_type":"code","source_file":"MuseCore/src/ui/components/TransportBar.tsx","source_location":null,"source_url":null,"captured_at":null,"author":null,"contributor":null},{"id":"analyzepage_analyzepage","label":"AnalyzePage","file_type":"code","source_file":"MuseCore/src/ui/pages/AnalyzePage.tsx","source_location":null,"source_url":null,"captured_at":null,"author":null,"contributor":null},{"id":"appshell_appshell","label":"AppShell (Root Layout)","file_type":"code","source_file":"MuseCore/src/ui/pages/AppShell.tsx","source_location":null,"source_url":null,"captured_at":null,"author":null,"contributor":null},{"id":"composepage_composepage","label":"ComposePage","file_type":"code","source_file":"MuseCore/src/ui/pages/ComposePage.tsx","source_location":null,"source_url":null,"captured_at":null,"author":null,"contributor":null},{"id":"drumscorepage_drumscorepage","label":"DrumScorePage (Legacy)","file_type":"code","source_file":"MuseCore/src/ui/pages/DrumScorePage.tsx","source_location":null,"source_url":null,"captured_at":null,"author":null,"contributor":null},{"id":"learnpage_learnpage","label":"LearnPage","file_type":"code","source_file":"MuseCore/src/ui/pages/LearnPage.tsx","source_location":null,"source_url":null,"captured_at":null,"author":null,"contributor":null},{"id":"librarypage_librarypage","label":"LibraryPage","file_type":"code","source_file":"MuseCore/src/ui/pages/LibraryPage.tsx","source_location":null,"source_url":null,"captured_at":null,"author":null,"contributor":null},{"id":"practicepage_practicepage","label":"PracticePage","file_type":"code","source_file":"MuseCore/src/ui/pages/PracticePage.tsx","source_location":null,"source_url":null,"captured_at":null,"author":null,"contributor":null},{"id":"scoreslibrarypage_scoreslibrarypage","label":"ScoresLibraryPage","file_type":"code","source_file":"MuseCore/src/ui/pages/ScoresLibraryPage.tsx","source_location":null,"source_url":null,"captured_at":null,"author":null,"contributor":null},{"id":"settingspage_settingspage","label":"SettingsPage (Full-page)","file_type":"code","source_file":"MuseCore/src/ui/pages/SettingsPage.tsx","source_location":null,"source_url":null,"captured_at":null,"author":null,"contributor":null},{"id":"gradientengine_gradientengine","label":"gradientEngine Utility","file_type":"code","source_file":"MuseCore/src/ui/utils/gradientEngine.ts","source_location":null,"source_url":null,"captured_at":null,"author":null,"contributor":null},{"id":"gradientengine_applygradienttodom","label":"applyGradientToDom Function","file_type":"code","source_file":"MuseCore/src/ui/utils/gradientEngine.ts","source_location":null,"source_url":null,"captured_at":null,"author":null,"contributor":null},{"id":"gradientengine_buildpreviewgradient","label":"buildPreviewGradient Function","file_type":"code","source_file":"MuseCore/src/ui/utils/gradientEngine.ts","source_location":null,"source_url":null,"captured_at":null,"author":null,"contributor":null},{"id":"viteconfig_viteconfig","label":"Vite Config","file_type":"code","source_file":"MuseCore/vite.config.ts","source_location":null,"source_url":null,"captured_at":null,"author":null,"contributor":null},{"id":"buildyml_buildyml","label":"CI/CD Build Workflow","file_type":"document","source_file":"MuseCore/.github/workflows/build.yml","source_location":null,"source_url":null,"captured_at":null,"author":null,"contributor":null},{"id":"indexhtml_indexhtml","label":"App Entry HTML","file_type":"document","source_file":"MuseCore/index.html","source_location":null,"source_url":null,"captured_at":null,"author":null,"contributor":null},{"id":"readme_readme","label":"README","file_type":"document","source_file":"MuseCore/README.md","source_location":null,"source_url":null,"captured_at":null,"author":null,"contributor":null},{"id":"projectstore_projectstore","label":"projectStore (Zustand)","file_type":"code","source_file":"MuseCore/src/store/projectStore.ts","source_location":null,"source_url":null,"captured_at":null,"author":null,"contributor":null},{"id":"settingsstore_settingsstore","label":"settingsStore (Zustand/persist)","file_type":"code","source_file":"MuseCore/src/store/settingsStore.ts","source_location":null,"source_url":null,"captured_at":null,"author":null,"contributor":null},{"id":"uistore_uistore","label":"uiStore (Zustand)","file_type":"code","source_file":"MuseCore/src/store/uiStore.ts","source_location":null,"source_url":null,"captured_at":null,"author":null,"contributor":null},{"id":"scoresstore_scoresstore","label":"scoresStore (Zustand)","file_type":"code","source_file":"MuseCore/src/store/scoresStore.ts","source_location":null,"source_url":null,"captured_at":null,"author":null,"contributor":null},{"id":"samplekitstore_samplekitstore","label":"sampleKitStore","file_type":"code","source_file":"MuseCore/src/store/sampleKitStore.ts","source_location":null,"source_url":null,"captured_at":null,"author":null,"contributor":null},{"id":"staffrenderer_staffrenderer","label":"staffRenderer","file_type":"code","source_file":"MuseCore/src/render/staffRenderer.ts","source_location":null,"source_url":null,"captured_at":null,"author":null,"contributor":null},{"id":"notepreviewengine_notepreviewengine","label":"notePreviewEngine","file_type":"code","source_file":"MuseCore/src/audio/notePreviewEngine.ts","source_location":null,"source_url":null,"captured_at":null,"author":null,"contributor":null},{"id":"limbanalyzer_limbanalyzer","label":"limbAnalyzer","file_type":"code","source_file":"MuseCore/src/analysis/limbAnalyzer.ts","source_location":null,"source_url":null,"captured_at":null,"author":null,"contributor":null},{"id":"sectionanalyzer_sectionanalyzer","label":"sectionAnalyzer","file_type":"code","source_file":"MuseCore/src/analysis/sectionAnalyzer.ts","source_location":null,"source_url":null,"captured_at":null,"author":null,"contributor":null},{"id":"playabilityengine_playabilityengine","label":"playabilityEngine","file_type":"code","source_file":"MuseCore/src/analysis/playabilityEngine.ts","source_location":null,"source_url":null,"captured_at":null,"author":null,"contributor":null},{"id":"energyflowanalyzer_energyflowanalyzer","label":"energyFlowAnalyzer","file_type":"code","source_file":"MuseCore/src/analysis/energyFlowAnalyzer.ts","source_location":null,"source_url":null,"captured_at":null,"author":null,"contributor":null},{"id":"sectionenergydetector_sectionenergydetector","label":"sectionEnergyDetector","file_type":"code","source_file":"MuseCore/src/analysis/sectionEnergyDetector.ts","source_location":null,"source_url":null,"captured_at":null,"author":null,"contributor":null},{"id":"ergonomicsengine_ergonomicsengine","label":"ergonomicsEngine","file_type":"code","source_file":"MuseCore/src/simulation/ergonomicsEngine.ts","source_location":null,"source_url":null,"captured_at":null,"author":null,"contributor":null},{"id":"transportcontroller_transportcontroller","label":"transportController","file_type":"code","source_file":"MuseCore/src/audio/transportController.ts","source_location":null,"source_url":null,"captured_at":null,"author":null,"contributor":null},{"id":"velocityanalyzer_velocityanalyzer","label":"velocityAnalyzer","file_type":"code","source_file":"MuseCore/src/render/velocityAnalyzer.ts","source_location":null,"source_url":null,"captured_at":null,"author":null,"contributor":null},{"id":"drumkitmanager_drumkitmanager","label":"drumKitManager","file_type":"code","source_file":"MuseCore/src/audio/drumKitManager.ts","source_location":null,"source_url":null,"captured_at":null,"author":null,"contributor":null},{"id":"drumpiecelibrary_drumpiecelibrary","label":"drumPieceLibrary","file_type":"code","source_file":"MuseCore/src/audio/drumPieceLibrary.ts","source_location":null,"source_url":null,"captured_at":null,"author":null,"contributor":null},{"id":"drumkitsampler_drumkitsampler","label":"drumKitSampler","file_type":"code","source_file":"MuseCore/src/audio/drumKitSampler.ts","source_location":null,"source_url":null,"captured_at":null,"author":null,"contributor":null},{"id":"samplekitengine_samplekitengine","label":"sampleKitEngine","file_type":"code","source_file":"MuseCore/src/audio/sampleKitEngine.ts","source_location":null,"source_url":null,"captured_at":null,"author":null,"contributor":null},{"id":"midiexporter_midiexporter","label":"midiExporter","file_type":"code","source_file":"MuseCore/src/core/midiExporter.ts","source_location":null,"source_url":null,"captured_at":null,"author":null,"contributor":null},{"id":"coretypes_coretypes","label":"Core Types","file_type":"code","source_file":"MuseCore/src/core/types.ts","source_location":null,"source_url":null,"captured_at":null,"author":null,"contributor":null},{"id":"appshell_appsection","label":"AppSection Type (navigation state)","file_type":"code","source_file":"MuseCore/src/ui/pages/AppShell.tsx","source_location":null,"source_url":null,"captured_at":null,"author":null,"contributor":null},{"id":"composepage_viewmode","label":"ViewMode (score/grid/drummer/animation/body)","file_type":"code","source_file":"MuseCore/src/ui/pages/ComposePage.tsx","source_location":null,"source_url":null,"captured_at":null,"author":null,"contributor":null},{"id":"settingsmodal_settingssections","label":"SettingsModal Section Registry (8 sections)","file_type":"code","source_file":"MuseCore/src/ui/components/SettingsModal.tsx","source_location":null,"source_url":null,"captured_at":null,"author":null,"contributor":null},{"id":"settingspage_settingssections","label":"SettingsPage Section Registry (8 sections)","file_type":"code","source_file":"MuseCore/src/ui/pages/SettingsPage.tsx","source_location":null,"source_url":null,"captured_at":null,"author":null,"contributor":null},{"id":"viteconfig_electron_crossorigin_plugin","label":"Electron Strip-Crossorigin Vite Plugin","file_type":"code","source_file":"MuseCore/vite.config.ts","source_location":null,"source_url":null,"captured_at":null,"author":null,"contributor":null},{"id":"buildyml_release_job","label":"GitHub Release Job (tag-triggered)","file_type":"document","source_file":"MuseCore/.github/workflows/build.yml","source_location":null,"source_url":null,"captured_at":null,"author":null,"contributor":null}],"edges":[{"source":"scorecanvas_scorecanvas","target":"staffrenderer_staffrenderer","relation":"calls","confidence":"EXTRACTED","confidence_score":1.0,"source_file":"MuseCore/src/ui/components/ScoreCanvas.tsx","source_location":null,"weight":1.0},{"source":"scorecanvas_scorecanvas","target":"notepreviewengine_notepreviewengine","relation":"calls","confidence":"EXTRACTED","confidence_score":1.0,"source_file":"MuseCore/src/ui/components/ScoreCanvas.tsx","source_location":null,"weight":1.0},{"source":"scorecanvas_scorecanvas","target":"projectstore_projectstore","relation":"calls","confidence":"EXTRACTED","confidence_score":1.0,"source_file":"MuseCore/src/ui/components/ScoreCanvas.tsx","source_location":null,"weight":1.0},{"source":"scorecanvas_scorecanvas","target":"limbanalyzer_limbanalyzer","relation":"references","confidence":"EXTRACTED","confidence_score":1.0,"source_file":"MuseCore/src/ui/components/ScoreCanvas.tsx","source_location":null,"weight":1.0},{"source":"scorecanvas_scorecanvas","target":"sectionanalyzer_sectionanalyzer","relation":"references","confidence":"EXTRACTED","confidence_score":1.0,"source_file":"MuseCore/src/ui/components/ScoreCanvas.tsx","source_location":null,"weight":1.0},{"source":"scorecanvas_scorecanvas","target":"playabilityengine_playabilityengine","relation":"references","confidence":"EXTRACTED","confidence_score":1.0,"source_file":"MuseCore/src/ui/components/ScoreCanvas.tsx","source_location":null,"weight":1.0},{"source":"scorecanvas_sectionoverlay","target":"sectionanalyzer_sectionanalyzer","relation":"references","confidence":"EXTRACTED","confidence_score":1.0,"source_file":"MuseCore/src/ui/components/ScoreCanvas.tsx","source_location":null,"weight":1.0},{"source":"scorecanvas_playabilityoverlay","target":"playabilityengine_playabilityengine","relation":"calls","confidence":"EXTRACTED","confidence_score":1.0,"source_file":"MuseCore/src/ui/components/ScoreCanvas.tsx","source_location":null,"weight":1.0},{"source":"scorecanvas_limboverlay","target":"limbanalyzer_limbanalyzer","relation":"references","confidence":"EXTRACTED","confidence_score":1.0,"source_file":"MuseCore/src/ui/components/ScoreCanvas.tsx","source_location":null,"weight":1.0},{"source":"scorecanvas_playhead_cursor","target":"scorecanvas_scorecanvas","relation":"implements","confidence":"EXTRACTED","confidence_score":1.0,"source_file":"MuseCore/src/ui/components/ScoreCanvas.tsx","source_location":null,"weight":1.0},{"source":"scorecanvas_click_preview","target":"notepreviewengine_notepreviewengine","relation":"calls","confidence":"EXTRACTED","confidence_score":1.0,"source_file":"MuseCore/src/ui/components/ScoreCanvas.tsx","source_location":null,"weight":1.0},{"source":"sectiontimeline_sectiontimeline","target":"sectionanalyzer_sectionanalyzer","relation":"references","confidence":"EXTRACTED","confidence_score":1.0,"source_file":"MuseCore/src/ui/components/SectionTimeline.tsx","source_location":null,"weight":1.0},{"source":"sectiontimeline_sectiontimeline","target":"playabilityengine_playabilityengine","relation":"references","confidence":"EXTRACTED","confidence_score":1.0,"source_file":"MuseCore/src/ui/components/SectionTimeline.tsx","source_location":null,"weight":1.0},{"source":"sectiontimeline_playabilitybadge","target":"sectiontimeline_sectiontimeline","relation":"implements","confidence":"EXTRACTED","confidence_score":1.0,"source_file":"MuseCore/src/ui/components/SectionTimeline.tsx","source_location":null,"weight":1.0},{"source":"settingsmodal_settingsmodal","target":"settingsstore_settingsstore","relation":"calls","confidence":"EXTRACTED","confidence_score":1.0,"source_file":"MuseCore/src/ui/components/SettingsModal.tsx","source_location":null,"weight":1.0},{"source":"settingsmodal_settingsmodal","target":"settingsmodal_settingssections","relation":"references","confidence":"EXTRACTED","confidence_score":1.0,"source_file":"MuseCore/src/ui/components/SettingsModal.tsx","source_location":null,"weight":1.0},{"source":"transportbar_transportbar","target":"projectstore_projectstore","relation":"calls","confidence":"EXTRACTED","confidence_score":1.0,"source_file":"MuseCore/src/ui/components/TransportBar.tsx","source_location":null,"weight":1.0},{"source":"transportbar_transportbar","target":"transportcontroller_transportcontroller","relation":"references","confidence":"EXTRACTED","confidence_score":1.0,"source_file":"MuseCore/src/ui/components/TransportBar.tsx","source_location":null,"weight":1.0},{"source":"transportbar_mixerstrip","target":"transportcontroller_transportcontroller","relation":"references","confidence":"EXTRACTED","confidence_score":1.0,"source_file":"MuseCore/src/ui/components/TransportBar.tsx","source_location":null,"weight":1.0},{"source":"analyzepage_analyzepage","target":"projectstore_projectstore","relation":"calls","confidence":"EXTRACTED","confidence_score":1.0,"source_file":"MuseCore/src/ui/pages/AnalyzePage.tsx","source_location":null,"weight":1.0},{"source":"analyzepage_analyzepage","target":"sectiontimeline_sectiontimeline","relation":"calls","confidence":"EXTRACTED","confidence_score":1.0,"source_file":"MuseCore/src/ui/pages/AnalyzePage.tsx","source_location":null,"weight":1.0},{"source":"analyzepage_analyzepage","target":"limbanalyzer_limbanalyzer","relation":"calls","confidence":"EXTRACTED","confidence_score":1.0,"source_file":"MuseCore/src/ui/pages/AnalyzePage.tsx","source_location":null,"weight":1.0},{"source":"analyzepage_analyzepage","target":"playabilityengine_playabilityengine","relation":"calls","confidence":"EXTRACTED","confidence_score":1.0,"source_file":"MuseCore/src/ui/pages/AnalyzePage.tsx","source_location":null,"weight":1.0},{"source":"analyzepage_analyzepage","target":"ergonomicsengine_ergonomicsengine","relation":"calls","confidence":"EXTRACTED","confidence_score":1.0,"source_file":"MuseCore/src/ui/pages/AnalyzePage.tsx","source_location":null,"weight":1.0},{"source":"analyzepage_analyzepage","target":"energyflowanalyzer_energyflowanalyzer","relation":"references","confidence":"EXTRACTED","confidence_score":1.0,"source_file":"MuseCore/src/ui/pages/AnalyzePage.tsx","source_location":null,"weight":1.0},{"source":"analyzepage_analyzepage","target":"sectionenergydetector_sectionenergydetector","relation":"calls","confidence":"EXTRACTED","confidence_score":1.0,"source_file":"MuseCore/src/ui/pages/AnalyzePage.tsx","source_location":null,"weight":1.0},{"source":"appshell_appshell","target":"composepage_composepage","relation":"calls","confidence":"EXTRACTED","confidence_score":1.0,"source_file":"MuseCore/src/ui/pages/AppShell.tsx","source_location":null,"weight":1.0},{"source":"appshell_appshell","target":"analyzepage_analyzepage","relation":"calls","confidence":"EXTRACTED","confidence_score":1.0,"source_file":"MuseCore/src/ui/pages/AppShell.tsx","source_location":null,"weight":1.0},{"source":"appshell_appshell","target":"practicepage_practicepage","relation":"calls","confidence":"EXTRACTED","confidence_score":1.0,"source_file":"MuseCore/src/ui/pages/AppShell.tsx","source_location":null,"weight":1.0},{"source":"appshell_appshell","target":"learnpage_learnpage","relation":"calls","confidence":"EXTRACTED","confidence_score":1.0,"source_file":"MuseCore/src/ui/pages/AppShell.tsx","source_location":null,"weight":1.0},{"source":"appshell_appshell","target":"librarypage_librarypage","relation":"calls","confidence":"EXTRACTED","confidence_score":1.0,"source_file":"MuseCore/src/ui/pages/AppShell.tsx","source_location":null,"weight":1.0},{"source":"appshell_appshell","target":"settingspage_settingspage","relation":"calls","confidence":"EXTRACTED","confidence_score":1.0,"source_file":"MuseCore/src/ui/pages/AppShell.tsx","source_location":null,"weight":1.0},{"source":"appshell_appshell","target":"transportbar_transportbar","relation":"calls","confidence":"EXTRACTED","confidence_score":1.0,"source_file":"MuseCore/src/ui/pages/AppShell.tsx","source_location":null,"weight":1.0},{"source":"appshell_appshell","target":"projectstore_projectstore","relation":"calls","confidence":"EXTRACTED","confidence_score":1.0,"source_file":"MuseCore/src/ui/pages/AppShell.tsx","source_location":null,"weight":1.0},{"source":"appshell_appshell","target":"settingsstore_settingsstore","relation":"references","confidence":"EXTRACTED","confidence_score":1.0,"source_file":"MuseCore/src/ui/pages/AppShell.tsx","source_location":null,"weight":1.0},{"source":"appshell_appsection","target":"appshell_appshell","relation":"implements","confidence":"EXTRACTED","confidence_score":1.0,"source_file":"MuseCore/src/ui/pages/AppShell.tsx","source_location":null,"weight":1.0},{"source":"composepage_composepage","target":"scorecanvas_scorecanvas","relation":"calls","confidence":"EXTRACTED","confidence_score":1.0,"source_file":"MuseCore/src/ui/pages/ComposePage.tsx","source_location":null,"weight":1.0},{"source":"composepage_composepage","target":"sectiontimeline_sectiontimeline","relation":"calls","confidence":"EXTRACTED","confidence_score":1.0,"source_file":"MuseCore/src/ui/pages/ComposePage.tsx","source_location":null,"weight":1.0},{"source":"composepage_composepage","target":"projectstore_projectstore","relation":"calls","confidence":"EXTRACTED","confidence_score":1.0,"source_file":"MuseCore/src/ui/pages/ComposePage.tsx","source_location":null,"weight":1.0},{"source":"composepage_composepage","target":"uistore_uistore","relation":"calls","confidence":"EXTRACTED","confidence_score":1.0,"source_file":"MuseCore/src/ui/pages/ComposePage.tsx","source_location":null,"weight":1.0},{"source":"composepage_composepage","target":"velocityanalyzer_velocityanalyzer","relation":"calls","confidence":"EXTRACTED","confidence_score":1.0,"source_file":"MuseCore/src/ui/pages/ComposePage.tsx","source_location":null,"weight":1.0},{"source":"composepage_composepage","target":"limbanalyzer_limbanalyzer","relation":"calls","confidence":"EXTRACTED","confidence_score":1.0,"source_file":"MuseCore/src/ui/pages/ComposePage.tsx","source_location":null,"weight":1.0},{"source":"composepage_composepage","target":"playabilityengine_playabilityengine","relation":"calls","confidence":"EXTRACTED","confidence_score":1.0,"source_file":"MuseCore/src/ui/pages/ComposePage.tsx","source_location":null,"weight":1.0},{"source":"composepage_viewmode","target":"composepage_composepage","relation":"implements","confidence":"EXTRACTED","confidence_score":1.0,"source_file":"MuseCore/src/ui/pages/ComposePage.tsx","source_location":null,"weight":1.0},{"source":"drumscorepage_drumscorepage","target":"scorecanvas_scorecanvas","relation":"calls","confidence":"EXTRACTED","confidence_score":1.0,"source_file":"MuseCore/src/ui/pages/DrumScorePage.tsx","source_location":null,"weight":1.0},{"source":"drumscorepage_drumscorepage","target":"sectiontimeline_sectiontimeline","relation":"calls","confidence":"EXTRACTED","confidence_score":1.0,"source_file":"MuseCore/src/ui/pages/DrumScorePage.tsx","source_location":null,"weight":1.0},{"source":"drumscorepage_drumscorepage","target":"transportbar_transportbar","relation":"calls","confidence":"EXTRACTED","confidence_score":1.0,"source_file":"MuseCore/src/ui/pages/DrumScorePage.tsx","source_location":null,"weight":1.0},{"source":"drumscorepage_drumscorepage","target":"projectstore_projectstore","relation":"calls","confidence":"EXTRACTED","confidence_score":1.0,"source_file":"MuseCore/src/ui/pages/DrumScorePage.tsx","source_location":null,"weight":1.0},{"source":"drumscorepage_drumscorepage","target":"midiexporter_midiexporter","relation":"calls","confidence":"EXTRACTED","confidence_score":1.0,"source_file":"MuseCore/src/ui/pages/DrumScorePage.tsx","source_location":null,"weight":1.0},{"source":"drumscorepage_drumscorepage","target":"velocityanalyzer_velocityanalyzer","relation":"calls","confidence":"EXTRACTED","confidence_score":1.0,"source_file":"MuseCore/src/ui/pages/DrumScorePage.tsx","source_location":null,"weight":1.0},{"source":"drumscorepage_drumscorepage","target":"limbanalyzer_limbanalyzer","relation":"calls","confidence":"EXTRACTED","confidence_score":1.0,"source_file":"MuseCore/src/ui/pages/DrumScorePage.tsx","source_location":null,"weight":1.0},{"source":"drumscorepage_drumscorepage","target":"playabilityengine_playabilityengine","relation":"calls","confidence":"EXTRACTED","confidence_score":1.0,"source_file":"MuseCore/src/ui/pages/DrumScorePage.tsx","source_location":null,"weight":1.0},{"source":"drumscorepage_drumscorepage","target":"transportcontroller_transportcontroller","relation":"calls","confidence":"EXTRACTED","confidence_score":1.0,"source_file":"MuseCore/src/ui/pages/DrumScorePage.tsx","source_location":null,"weight":1.0},{"source":"learnpage_learnpage","target":"projectstore_projectstore","relation":"calls","confidence":"EXTRACTED","confidence_score":1.0,"source_file":"MuseCore/src/ui/pages/LearnPage.tsx","source_location":null,"weight":1.0},{"source":"librarypage_librarypage","target":"projectstore_projectstore","relation":"calls","confidence":"EXTRACTED","confidence_score":1.0,"source_file":"MuseCore/src/ui/pages/LibraryPage.tsx","source_location":null,"weight":1.0},{"source":"librarypage_librarypage","target":"scoreslibrarypage_scoreslibrarypage","relation":"calls","confidence":"EXTRACTED","confidence_score":1.0,"source_file":"MuseCore/src/ui/pages/LibraryPage.tsx","source_location":null,"weight":1.0},{"source":"librarypage_librarypage","target":"drumkitmanager_drumkitmanager","relation":"references","confidence":"EXTRACTED","confidence_score":1.0,"source_file":"MuseCore/src/ui/pages/LibraryPage.tsx","source_location":null,"weight":1.0},{"source":"librarypage_librarypage","target":"drumpiecelibrary_drumpiecelibrary","relation":"references","confidence":"EXTRACTED","confidence_score":1.0,"source_file":"MuseCore/src/ui/pages/LibraryPage.tsx","source_location":null,"weight":1.0},{"source":"librarypage_librarypage","target":"drumkitsampler_drumkitsampler","relation":"calls","confidence":"EXTRACTED","confidence_score":1.0,"source_file":"MuseCore/src/ui/pages/LibraryPage.tsx","source_location":null,"weight":1.0},{"source":"librarypage_librarypage","target":"samplekitengine_samplekitengine","relation":"calls","confidence":"EXTRACTED","confidence_score":1.0,"source_file":"MuseCore/src/ui/pages/LibraryPage.tsx","source_location":null,"weight":1.0},{"source":"librarypage_librarypage","target":"samplekitstore_samplekitstore","relation":"calls","confidence":"EXTRACTED","confidence_score":1.0,"source_file":"MuseCore/src/ui/pages/LibraryPage.tsx","source_location":null,"weight":1.0},{"source":"practicepage_practicepage","target":"projectstore_projectstore","relation":"calls","confidence":"EXTRACTED","confidence_score":1.0,"source_file":"MuseCore/src/ui/pages/PracticePage.tsx","source_location":null,"weight":1.0},{"source":"practicepage_practicepage","target":"scorecanvas_scorecanvas","relation":"calls","confidence":"EXTRACTED","confidence_score":1.0,"source_file":"MuseCore/src/ui/pages/PracticePage.tsx","source_location":null,"weight":1.0},{"source":"scoreslibrarypage_scoreslibrarypage","target":"scoresstore_scoresstore","relation":"calls","confidence":"EXTRACTED","confidence_score":1.0,"source_file":"MuseCore/src/ui/pages/ScoresLibraryPage.tsx","source_location":null,"weight":1.0},{"source":"settingspage_settingspage","target":"settingsstore_settingsstore","relation":"calls","confidence":"EXTRACTED","confidence_score":1.0,"source_file":"MuseCore/src/ui/pages/SettingsPage.tsx","source_location":null,"weight":1.0},{"source":"settingspage_settingspage","target":"gradientengine_buildpreviewgradient","relation":"calls","confidence":"EXTRACTED","confidence_score":1.0,"source_file":"MuseCore/src/ui/pages/SettingsPage.tsx","source_location":null,"weight":1.0},{"source":"settingspage_settingspage","target":"settingspage_settingssections","relation":"references","confidence":"EXTRACTED","confidence_score":1.0,"source_file":"MuseCore/src/ui/pages/SettingsPage.tsx","source_location":null,"weight":1.0},{"source":"gradientengine_applygradienttodom","target":"settingsstore_settingsstore","relation":"references","confidence":"EXTRACTED","confidence_score":1.0,"source_file":"MuseCore/src/ui/utils/gradientEngine.ts","source_location":null,"weight":1.0},{"source":"gradientengine_buildpreviewgradient","target":"gradientengine_gradientengine","relation":"implements","confidence":"EXTRACTED","confidence_score":1.0,"source_file":"MuseCore/src/ui/utils/gradientEngine.ts","source_location":null,"weight":1.0},{"source":"gradientengine_applygradienttodom","target":"gradientengine_gradientengine","relation":"implements","confidence":"EXTRACTED","confidence_score":1.0,"source_file":"MuseCore/src/ui/utils/gradientEngine.ts","source_location":null,"weight":1.0},{"source":"viteconfig_electron_crossorigin_plugin","target":"viteconfig_viteconfig","relation":"implements","confidence":"EXTRACTED","confidence_score":1.0,"source_file":"MuseCore/vite.config.ts","source_location":null,"weight":1.0},{"source":"buildyml_release_job","target":"buildyml_buildyml","relation":"implements","confidence":"EXTRACTED","confidence_score":1.0,"source_file":"MuseCore/.github/workflows/build.yml","source_location":null,"weight":1.0},{"source":"indexhtml_indexhtml","target":"viteconfig_viteconfig","relation":"references","confidence":"EXTRACTED","confidence_score":1.0,"source_file":"MuseCore/index.html","source_location":null,"weight":1.0},{"source":"settingspage_settingspage","target":"settingsmodal_settingsmodal","relation":"semantically_similar_to","confidence":"INFERRED","confidence_score":0.95,"source_file":"MuseCore/src/ui/pages/SettingsPage.tsx","source_location":null,"weight":0.85},{"source":"composepage_composepage","target":"drumscorepage_drumscorepage","relation":"semantically_similar_to","confidence":"INFERRED","confidence_score":0.95,"source_file":"MuseCore/src/ui/pages/ComposePage.tsx","source_location":null,"weight":0.85},{"source":"scorecanvas_scorecanvas","target":"composepage_viewmode","relation":"shares_data_with","confidence":"INFERRED","confidence_score":0.95,"source_file":"MuseCore/src/ui/pages/ComposePage.tsx","source_location":null,"weight":0.9},{"source":"transportbar_transportbar","target":"appshell_appshell","relation":"shares_data_with","confidence":"INFERRED","confidence_score":0.85,"source_file":"MuseCore/src/ui/pages/AppShell.tsx","source_location":null,"weight":0.8},{"source":"gradientengine_applygradienttodom","target":"settingspage_settingspage","relation":"references","confidence":"INFERRED","confidence_score":0.85,"source_file":"MuseCore/src/ui/utils/gradientEngine.ts","source_location":null,"weight":0.8},{"source":"appshell_appshell","target":"uistore_uistore","relation":"references","confidence":"INFERRED","confidence_score":0.75,"source_file":"MuseCore/src/ui/pages/AppShell.tsx","source_location":null,"weight":0.7},{"source":"scorecanvas_sectionoverlay","target":"scorecanvas_playabilityoverlay","relation":"semantically_similar_to","confidence":"INFERRED","confidence_score":0.85,"source_file":"MuseCore/src/ui/components/ScoreCanvas.tsx","source_location":null,"weight":0.75},{"source":"scorecanvas_sectionoverlay","target":"scorecanvas_limboverlay","relation":"semantically_similar_to","confidence":"INFERRED","confidence_score":0.85,"source_file":"MuseCore/src/ui/components/ScoreCanvas.tsx","source_location":null,"weight":0.75},{"source":"viteconfig_viteconfig","target":"buildyml_buildyml","relation":"conceptually_related_to","confidence":"INFERRED","confidence_score":0.85,"source_file":"MuseCore/vite.config.ts","source_location":null,"weight":0.8},{"source":"librarypage_librarypage","target":"appshell_appshell","relation":"shares_data_with","confidence":"INFERRED","confidence_score":0.85,"source_file":"MuseCore/src/ui/pages/LibraryPage.tsx","source_location":null,"weight":0.8},{"source":"scoreslibrarypage_scoreslibrarypage","target":"librarypage_librarypage","relation":"implements","confidence":"INFERRED","confidence_score":0.95,"source_file":"MuseCore/src/ui/pages/LibraryPage.tsx","source_location":null,"weight":0.9},{"source":"sectiontimeline_sectiontimeline","target":"scorecanvas_sectionoverlay","relation":"semantically_similar_to","confidence":"INFERRED","confidence_score":0.85,"source_file":"MuseCore/src/ui/components/SectionTimeline.tsx","source_location":null,"weight":0.8},{"source":"topbar_topbar","target":"composepage_composepage","relation":"semantically_similar_to","confidence":"INFERRED","confidence_score":0.75,"source_file":"MuseCore/src/ui/components/TopBar.tsx","source_location":null,"weight":0.65},{"source":"analyzepage_analyzepage","target":"composepage_composepage","relation":"shares_data_with","confidence":"INFERRED","confidence_score":0.95,"source_file":"MuseCore/src/ui/pages/AnalyzePage.tsx","source_location":null,"weight":0.9},{"source":"practicepage_practicepage","target":"transportbar_transportbar","relation":"shares_data_with","confidence":"INFERRED","confidence_score":0.85,"source_file":"MuseCore/src/ui/pages/PracticePage.tsx","source_location":null,"weight":0.8}],"hyperedges":[{"id":"score_overlay_system","label":"Score Overlay System (Section + Playability + Limb)","nodes":["scorecanvas_sectionoverlay","scorecanvas_playabilityoverlay","scorecanvas_limboverlay"],"relation":"implement","confidence":"EXTRACTED","confidence_score":1.0,"source_file":"MuseCore/src/ui/components/ScoreCanvas.tsx"},{"id":"app_navigation_pages","label":"App Navigation Pages (Compose / Analyze / Practice / Learn / Library / Settings)","nodes":["composepage_composepage","analyzepage_analyzepage","practicepage_practicepage","learnpage_learnpage","librarypage_librarypage","settingspage_settingspage"],"relation":"participate_in","confidence":"EXTRACTED","confidence_score":1.0,"source_file":"MuseCore/src/ui/pages/AppShell.tsx"},{"id":"settings_dual_surface","label":"Dual Settings Surface (SettingsModal + SettingsPage both backed by settingsStore)","nodes":["settingsmodal_settingsmodal","settingspage_settingspage","settingsstore_settingsstore"],"relation":"participate_in","confidence":"EXTRACTED","confidence_score":1.0,"source_file":"MuseCore/src/ui/pages/SettingsPage.tsx"}],"input_tokens":0,"output_tokens":0}
